{"stats":{"minecraft:used":{"minecraft:purple_stained_glass":3,"minecraft:oak_fence":4,"minecraft:cyan_terracotta":372,"teletubbies:dipsy_spawn_egg":1,"teletubbies:nin_spawn_egg":1,"teletubbies:window":29,"teletubbies:mimi_spawn_egg":1,"teletubbies:ba_spawn_egg":1,"minecraft:quartz_slab":6,"minecraft:yellow_stained_glass":4,"minecraft:red_concrete":60,"minecraft:red_stained_glass":5,"teletubbies:duggledee_spawn_egg":1,"teletubbies:laalaa_spawn_egg":1,"minecraft:polished_andesite_stairs":1,"teletubbies:umpiepumpie_spawn_egg":1,"minecraft:chest":2,"minecraft:stone":94,"minecraft:structure_void":3333,"minecraft:quartz_stairs":18,"minecraft:stone_brick_stairs":26,"minecraft:structure_block":47,"minecraft:smooth_quartz_stairs":1,"minecraft:purple_concrete":66,"minecraft:glowstone":7,"minecraft:diamond_sword":53,"minecraft:redstone_lamp":15,"teletubbies:ping_spawn_egg":1,"minecraft:lime_concrete":58,"minecraft:purple_bed":1,"minecraft:light_blue_concrete":345,"minecraft:lime_stained_glass":16,"minecraft:lime_bed":1,"teletubbies:noonoo_spawn_egg":1,"minecraft:red_bed":1,"teletubbies:po_scooter":1,"minecraft:blast_furnace":1,"teletubbies:full_grass":2523,"teletubbies:custard_machine":2,"minecraft:yellow_concrete":63,"minecraft:white_stained_glass":1,"minecraft:stone_stairs":3,"minecraft:yellow_bed":1,"teletubbies:po_spawn_egg":1,"minecraft:white_concrete":190,"teletubbies:tinkywinky_spawn_egg":1,"teletubbies:daadaa_spawn_egg":1,"minecraft:oak_fence_gate":2,"minecraft:dark_oak_door":4,"teletubbies:toast_machine":2,"teletubbies:ruru_spawn_egg":1,"minecraft:redstone_torch":27},"minecraft:killed":{"teletubbies:nin":1,"minecraft:trader_llama":2,"teletubbies:duggledee":1,"teletubbies:noonoo":1,"teletubbies:mimi":1,"teletubbies:ba":2,"teletubbies:daadaa":1,"teletubbies:umpiepumpie":1,"teletubbies:ping":1,"minecraft:bat":5,"minecraft:wandering_trader":1,"teletubbies:laalaa":1,"teletubbies:po":1,"teletubbies:ruru":1},"minecraft:mined":{"teletubbies:window":17},"minecraft:picked_up":{"minecraft:dark_oak_door":3,"minecraft:white_stained_glass_pane":21,"teletubbies:laalaa_stick":1,"minecraft:cyan_stained_glass_pane":27,"teletubbies:po_stick":1,"teletubbies:noonoo_eyes":1,"teletubbies:toast":2},"minecraft:custom":{"minecraft:time_since_rest":76832,"minecraft:sprint_one_cm":103817,"minecraft:damage_taken":40,"minecraft:walk_one_cm":99408,"minecraft:mob_kills":22,"minecraft:damage_dealt":2682,"minecraft:fly_one_cm":1463722,"minecraft:open_chest":1,"minecraft:play_one_minute":220298,"minecraft:crouch_one_cm":11816,"minecraft:deaths":1,"minecraft:sneak_time":7144,"minecraft:jump":461,"minecraft:interact_with_blast_furnace":1,"minecraft:leave_game":15,"minecraft:time_since_death":76810,"minecraft:fall_one_cm":886}},"DataVersion":1976}